odoo/addons/pos_available_in_pos_unlink/README.rst
odoo/addons/pos_available_in_pos_unlink/__init__.py
odoo/addons/pos_available_in_pos_unlink/__manifest__.py
odoo/addons/pos_available_in_pos_unlink/i18n/beesdoo_pos.pot
odoo/addons/pos_available_in_pos_unlink/i18n/pos_available_in_pos_unlink.pot
odoo/addons/pos_available_in_pos_unlink/models/__init__.py
odoo/addons/pos_available_in_pos_unlink/models/product.py
odoo/addons/pos_available_in_pos_unlink/readme/CONTRIBUTORS.rst
odoo/addons/pos_available_in_pos_unlink/readme/DESCRIPTION.rst
odoo/addons/pos_available_in_pos_unlink/static/description/index.html
odoo12_addon_pos_available_in_pos_unlink-12.0.2.0.2.dist-info/METADATA
odoo12_addon_pos_available_in_pos_unlink-12.0.2.0.2.dist-info/WHEEL
odoo12_addon_pos_available_in_pos_unlink-12.0.2.0.2.dist-info/top_level.txt
odoo12_addon_pos_available_in_pos_unlink-12.0.2.0.2.dist-info/RECORD
