Metadata-Version: 2.1
Name: odoo12-addon-pos_available_in_pos_unlink
Version: 12.0.2.0.2
Summary: Maintains "Available in POS" (`available_in_pos`) value when unchecking "Can be Sold" (`sale_ok`).
Home-page: https://coopiteasy.be
Author: BEES coop - Cellule IT, Coop IT Easy SC
License: AGPL-3
Classifier: Programming Language :: Python
Classifier: Framework :: Odoo
Classifier: Framework :: Odoo :: 12.0
Classifier: License :: OSI Approved :: GNU Affero General Public License v3
Requires-Python: >=3.5
Requires-Dist: odoo<12.1dev,>=12.0a
